{
  "device_consumption": {
    "single": {
      "usage_profile": {"LVE": 2},
      "consumption_variation": 0.5
    },
    "family": {
      "usage_profile": {"LVE": 2},
      "consumption_variation": 0.5
    }
  },

  "user_profile":{
    "family": {
      "profile": [[19.5, 0.5]],

      "period": 24,
      "offset": 0,

      "start_time_variation": 1.5,
      "duration_variation": 0.5
    },

    "single": {
      "profile": [[19.5, 0.25]],

      "period": 24,
      "offset": 0,

      "start_time_variation": 1.5,
      "duration_variation": 0.5
    }
  }

}